pyblish_qml/__init__.py
pyblish_qml/__main__.py
pyblish_qml/api.py
pyblish_qml/app.py
pyblish_qml/compat.py
pyblish_qml/control.py
pyblish_qml/host.py
pyblish_qml/icon.ico
pyblish_qml/models.py
pyblish_qml/settings.py
pyblish_qml/splash.png
pyblish_qml/util.py
pyblish_qml/version.py
pyblish_qml/ipc/__init__.py
pyblish_qml/ipc/client.py
pyblish_qml/ipc/formatting.py
pyblish_qml/ipc/mocking.py
pyblish_qml/ipc/schema.py
pyblish_qml/ipc/server.py
pyblish_qml/ipc/service.py
pyblish_qml/ipc/schema/_changes.json
pyblish_qml/ipc/schema/_state.json
pyblish_qml/ipc/schema/context.json
pyblish_qml/ipc/schema/error.json
pyblish_qml/ipc/schema/instance.json
pyblish_qml/ipc/schema/plugin.json
pyblish_qml/ipc/schema/record.json
pyblish_qml/ipc/schema/result.json
pyblish_qml/qml/CommentBox.qml
pyblish_qml/qml/Delegates.js
pyblish_qml/qml/Footer.qml
pyblish_qml/qml/List.qml
pyblish_qml/qml/Message.qml
pyblish_qml/qml/Overview.qml
pyblish_qml/qml/Properties.qml
pyblish_qml/qml/Terminal.qml
pyblish_qml/qml/app.qml
pyblish_qml/qml/main.qml
pyblish_qml/qml/Perspective/Gadget.qml
pyblish_qml/qml/Perspective/Header.qml
pyblish_qml/qml/Perspective/Page.qml
pyblish_qml/qml/Perspective/Title.qml
pyblish_qml/qml/Perspective/Viewport.qml
pyblish_qml/qml/Perspective/qmldir
pyblish_qml/qml/Perspective/tests/tst_Perspective.py
pyblish_qml/qml/Perspective/tests/tst_Perspective.qml
pyblish_qml/qml/Pyblish/Action.qml
pyblish_qml/qml/Pyblish/ActionBar.qml
pyblish_qml/qml/Pyblish/AwesomeButton.qml
pyblish_qml/qml/Pyblish/AwesomeIcon.qml
pyblish_qml/qml/Pyblish/Button.qml
pyblish_qml/qml/Pyblish/CheckBox.qml
pyblish_qml/qml/Pyblish/Global.qml
pyblish_qml/qml/Pyblish/Icon.qml
pyblish_qml/qml/Pyblish/IconButton.qml
pyblish_qml/qml/Pyblish/Ink.qml
pyblish_qml/qml/Pyblish/Label.qml
pyblish_qml/qml/Pyblish/Object.qml
pyblish_qml/qml/Pyblish/ProgressBar.qml
pyblish_qml/qml/Pyblish/ScrollHint.qml
pyblish_qml/qml/Pyblish/Scrollbar.qml
pyblish_qml/qml/Pyblish/Spacer.qml
pyblish_qml/qml/Pyblish/SpinBox.qml
pyblish_qml-1.11.5.dist-info/LICENSE
pyblish_qml-1.11.5.dist-info/METADATA
pyblish_qml-1.11.5.dist-info/WHEEL
pyblish_qml-1.11.5.dist-info/top_level.txt
pyblish_qml-1.11.5.dist-info/RECORD
